bakdroid/__init__.py
bakdroid/cli.py
bakdroid/crypto.py
bakdroid/header.py
bakdroid/unpacker.py
bakdroid-0.1.1.dist-info/METADATA
bakdroid-0.1.1.dist-info/WHEEL
bakdroid-0.1.1.dist-info/entry_points.txt
bakdroid-0.1.1.dist-info/RECORD
