Metadata-Version: 2.1
Name: bakdroid
Version: 0.1.1
Summary: A command-line tool to unpack backup files with decryption and decompression support.
Home-page: https://github.com/zahidaz/bakdroid
License: MIT
Keywords: backup,decryption,compression,cli,tool,android,android backup
Author: Ahmad Zubair Zahid
Requires-Python: >=3.9,<4.0
Classifier: License :: OSI Approved :: MIT License
Classifier: Programming Language :: Python :: 3
Classifier: Programming Language :: Python :: 3.9
Classifier: Programming Language :: Python :: 3.10
Classifier: Programming Language :: Python :: 3.11
Classifier: Programming Language :: Python :: 3.12
Classifier: Programming Language :: Python :: 3.13
Requires-Dist: click (>=8.1.7,<9.0.0)
Requires-Dist: cryptography (>=43.0.3,<44.0.0)
Project-URL: Repository, https://github.com/zahidaz/bakdroid
